weldx_widgets/.gitignore
weldx_widgets/__init__.py
weldx_widgets/generic.py
weldx_widgets/widget_base.py
weldx_widgets/widget_evaluate.py
weldx_widgets/widget_factory.py
weldx_widgets/widget_gas.py
weldx_widgets/widget_gmaw.py
weldx_widgets/widget_groove_sel.py
weldx_widgets/widget_measurement.py
weldx_widgets/widget_weldx_file.py
weldx_widgets/tests/__init__.py
weldx_widgets/tests/conftest.py
weldx_widgets/tests/test_eval.py
weldx_widgets/tests/test_gas.py
weldx_widgets/tests/test_generic.py
weldx_widgets/tests/test_groove_sel.py
weldx_widgets/tests/test_k3d.py
weldx_widgets/tests/test_process.py
weldx_widgets/tests/test_visualization.py
weldx_widgets/tests/util.py
weldx_widgets/visualization/__init__.py
weldx_widgets/visualization/colors.py
weldx_widgets/visualization/csm_k3d.py
weldx_widgets/visualization/csm_mpl.py
weldx_widgets/visualization/types.py
weldx_widgets-0.3.0.dist-info/licenses/LICENSE
weldx_widgets-0.3.0.dist-info/METADATA
weldx_widgets-0.3.0.dist-info/WHEEL
weldx_widgets-0.3.0.dist-info/top_level.txt
weldx_widgets-0.3.0.dist-info/RECORD
