Metadata-Version: 2.4
Name: weldx-widgets
Version: 0.3.0
Summary: Python based widgets for the weldx core package
Author-email: Çağtay Fabry <cagtay.fabry@bam.de>, "Martin K. Scherer" <martin.scherer@bam.de>
License: BSD 3-Clause License
Project-URL: bug_tracker, https://github.com/BAMweldx/weldx-widgets/issues
Project-URL: changelog, https://github.com/BAMweldx/weldx-widgets/blob/master/CHANGELOG.md
Project-URL: documentation, https://weldx.readthedocs.io
Project-URL: repository, https://github.com/BAMweldx/weldx-widgets
Keywords: ipywidgets,weldx,widgets
Classifier: Development Status :: 3 - Alpha
Classifier: Intended Audience :: Science/Research
Classifier: License :: OSI Approved :: BSD License
Classifier: Natural Language :: English
Classifier: Operating System :: OS Independent
Classifier: Programming Language :: Python
Classifier: Programming Language :: Python :: 3 :: Only
Classifier: Programming Language :: Python :: 3.9
Classifier: Programming Language :: Python :: 3.10
Classifier: Programming Language :: Python :: 3.11
Classifier: Programming Language :: Python :: 3.12
Classifier: Programming Language :: Python :: 3.13
Classifier: Topic :: Scientific/Engineering :: Physics
Requires-Python: >=3.9
License-File: LICENSE
Requires-Dist: bidict
Requires-Dist: ipyfilechooser
Requires-Dist: ipympl
Requires-Dist: ipython>=8
Requires-Dist: ipywidgets>=8.1
Requires-Dist: k3d>=2.12
Requires-Dist: matplotlib>=3.8
Requires-Dist: numpy
Requires-Dist: pint
Requires-Dist: tqdm
Requires-Dist: weldx>=0.6
Provides-Extra: test
Requires-Dist: pytest-cov; extra == "test"
Requires-Dist: pytest-xdist; extra == "test"
Dynamic: license-file
